{
	"credit": "Made with Blockbench",
	"texture_size": [64, 64],
	"textures": {
		"3": "stabxmodernguns:item/ak_universal_advanced_suppressor"
	},
	"elements": [
		{
			"name": "octagon",
			"from": [7.77525, 2.3458, -13.41875],
			"to": [8.14804, 2.4458, -12.38125],
			"rotation": {"angle": -45, "axis": "z", "origin": [7.96065, 2.7948, -13.53281]},
			"faces": {
				"north": {"uv": [8, 8, 9, 9], "texture": "#3"},
				"east": {"uv": [9, 0, 10, 1], "texture": "#3"},
				"south": {"uv": [9, 1, 10, 2], "texture": "#3"},
				"west": {"uv": [2, 9, 3, 10], "texture": "#3"},
				"up": {"uv": [4, 10, 3, 9], "texture": "#3"},
				"down": {"uv": [10, 5, 9, 6], "texture": "#3"}
			}
		},
		{
			"name": "octagon",
			"from": [7.77525, 3.1458, -13.41875],
			"to": [8.14804, 3.2458, -12.38125],
			"rotation": {"angle": -45, "axis": "z", "origin": [7.96065, 2.7948, -13.53281]},
			"faces": {
				"north": {"uv": [9, 6, 10, 7], "texture": "#3"},
				"east": {"uv": [8, 9, 9, 10], "texture": "#3"},
				"south": {"uv": [9, 8, 10, 9], "texture": "#3"},
				"west": {"uv": [9, 9, 10, 10], "texture": "#3"},
				"up": {"uv": [11, 1, 10, 0], "texture": "#3"},
				"down": {"uv": [11, 1, 10, 2], "texture": "#3"}
			}
		},
		{
			"name": "octagon",
			"from": [7.51206, 2.6084, -13.41875],
			"to": [7.61206, 2.9812, -12.38125],
			"rotation": {"angle": 0, "axis": "y", "origin": [7.96065, 2.7948, -13.53281]},
			"faces": {
				"north": {"uv": [2, 10, 3, 11], "texture": "#3"},
				"east": {"uv": [3, 10, 4, 11], "texture": "#3"},
				"south": {"uv": [10, 3, 11, 4], "texture": "#3"},
				"west": {"uv": [4, 10, 5, 11], "texture": "#3"},
				"up": {"uv": [11, 6, 10, 5], "texture": "#3"},
				"down": {"uv": [7, 10, 6, 11], "texture": "#3"}
			}
		},
		{
			"name": "octagon",
			"from": [8.30643, 2.6084, -13.41875],
			"to": [8.41206, 2.9812, -12.38125],
			"rotation": {"angle": 0, "axis": "y", "origin": [7.96065, 2.7948, -13.53281]},
			"faces": {
				"north": {"uv": [10, 6, 11, 7], "texture": "#3"},
				"east": {"uv": [10, 7, 11, 8], "texture": "#3"},
				"south": {"uv": [8, 10, 9, 11], "texture": "#3"},
				"west": {"uv": [10, 8, 11, 9], "texture": "#3"},
				"up": {"uv": [10, 11, 9, 10], "texture": "#3"},
				"down": {"uv": [11, 9, 10, 10], "texture": "#3"}
			}
		},
		{
			"name": "octagon",
			"from": [8.31165, 2.6094, -13.41875],
			"to": [8.41165, 2.98219, -12.38125],
			"rotation": {"angle": -45, "axis": "z", "origin": [7.96065, 2.7948, -13.53281]},
			"faces": {
				"north": {"uv": [10, 10, 11, 11], "texture": "#3"},
				"east": {"uv": [0, 11, 1, 12], "texture": "#3"},
				"south": {"uv": [11, 0, 12, 1], "texture": "#3"},
				"west": {"uv": [1, 11, 2, 12], "texture": "#3"},
				"up": {"uv": [12, 2, 11, 1], "texture": "#3"},
				"down": {"uv": [3, 11, 2, 12], "texture": "#3"}
			}
		},
		{
			"name": "octagon",
			"from": [7.51165, 2.6094, -13.41875],
			"to": [7.61165, 2.98219, -12.38125],
			"rotation": {"angle": -45, "axis": "z", "origin": [7.96065, 2.7948, -13.53281]},
			"faces": {
				"north": {"uv": [11, 2, 12, 3], "texture": "#3"},
				"east": {"uv": [3, 11, 4, 12], "texture": "#3"},
				"south": {"uv": [11, 3, 12, 4], "texture": "#3"},
				"west": {"uv": [4, 11, 5, 12], "texture": "#3"},
				"up": {"uv": [12, 5, 11, 4], "texture": "#3"},
				"down": {"uv": [6, 11, 5, 12], "texture": "#3"}
			}
		},
		{
			"name": "octagon",
			"from": [7.77567, 2.3448, -13.41875],
			"to": [8.14846, 2.4448, -12.38125],
			"rotation": {"angle": 0, "axis": "y", "origin": [7.96065, 2.7948, -13.53281]},
			"faces": {
				"north": {"uv": [11, 5, 12, 6], "texture": "#3"},
				"east": {"uv": [6, 11, 7, 12], "texture": "#3"},
				"south": {"uv": [11, 6, 12, 7], "texture": "#3"},
				"west": {"uv": [7, 11, 8, 12], "texture": "#3"},
				"up": {"uv": [12, 8, 11, 7], "texture": "#3"},
				"down": {"uv": [9, 11, 8, 12], "texture": "#3"}
			}
		},
		{
			"name": "octagon",
			"from": [7.77567, 3.1448, -13.41875],
			"to": [8.14846, 3.2448, -12.38125],
			"rotation": {"angle": 0, "axis": "y", "origin": [7.96065, 2.7948, -13.53281]},
			"faces": {
				"north": {"uv": [11, 8, 12, 9], "texture": "#3"},
				"east": {"uv": [9, 11, 10, 12], "texture": "#3"},
				"south": {"uv": [11, 9, 12, 10], "texture": "#3"},
				"west": {"uv": [10, 11, 11, 12], "texture": "#3"},
				"up": {"uv": [12, 11, 11, 10], "texture": "#3"},
				"down": {"uv": [12, 11, 11, 12], "texture": "#3"}
			}
		},
		{
			"name": "octagon",
			"from": [7.75663, 2.2875, -16],
			"to": [8.17084, 2.45, -13.175],
			"rotation": {"angle": 45, "axis": "z", "origin": [7.96373, 2.7875, -13.0875]},
			"faces": {
				"north": {"uv": [0, 12, 1, 13], "texture": "#3"},
				"east": {"uv": [0, 0, 3, 1], "texture": "#3"},
				"south": {"uv": [12, 0, 13, 1], "texture": "#3"},
				"west": {"uv": [0, 1, 3, 2], "texture": "#3"},
				"up": {"uv": [1, 5, 0, 2], "texture": "#3"},
				"down": {"uv": [2, 2, 1, 5], "texture": "#3"}
			}
		},
		{
			"name": "octagon",
			"from": [7.75663, 2.2875, -16],
			"to": [8.17084, 2.41875, -13.175],
			"rotation": {"angle": 0, "axis": "y", "origin": [7.96373, 2.7875, -13.0875]},
			"faces": {
				"north": {"uv": [1, 12, 2, 13], "texture": "#3"},
				"east": {"uv": [2, 2, 5, 3], "texture": "#3"},
				"south": {"uv": [12, 1, 13, 2], "texture": "#3"},
				"west": {"uv": [3, 0, 6, 1], "texture": "#3"},
				"up": {"uv": [3, 6, 2, 3], "texture": "#3"},
				"down": {"uv": [4, 3, 3, 6], "texture": "#3"}
			}
		},
		{
			"name": "octagon",
			"from": [7.75663, 3.15625, -16],
			"to": [8.17084, 3.2875, -13.175],
			"rotation": {"angle": 45, "axis": "z", "origin": [7.96373, 2.7875, -13.0875]},
			"faces": {
				"north": {"uv": [2, 12, 3, 13], "texture": "#3"},
				"east": {"uv": [3, 1, 6, 2], "texture": "#3"},
				"south": {"uv": [12, 2, 13, 3], "texture": "#3"},
				"west": {"uv": [4, 3, 7, 4], "texture": "#3"},
				"up": {"uv": [5, 7, 4, 4], "texture": "#3"},
				"down": {"uv": [1, 5, 0, 8], "texture": "#3"}
			}
		},
		{
			"name": "octagon",
			"from": [7.75663, 3.15625, -16],
			"to": [8.17084, 3.2875, -13.175],
			"rotation": {"angle": 0, "axis": "y", "origin": [7.96373, 2.7875, -13.0875]},
			"faces": {
				"north": {"uv": [3, 12, 4, 13], "texture": "#3"},
				"east": {"uv": [5, 2, 8, 3], "texture": "#3"},
				"south": {"uv": [12, 3, 13, 4], "texture": "#3"},
				"west": {"uv": [5, 4, 8, 5], "texture": "#3"},
				"up": {"uv": [2, 8, 1, 5], "texture": "#3"},
				"down": {"uv": [6, 5, 5, 8], "texture": "#3"}
			}
		},
		{
			"name": "octagon",
			"from": [7.46373, 2.58039, -16],
			"to": [7.59498, 2.99461, -13.175],
			"rotation": {"angle": 45, "axis": "z", "origin": [7.96373, 2.7875, -13.0875]},
			"faces": {
				"north": {"uv": [4, 12, 5, 13], "texture": "#3"},
				"east": {"uv": [6, 0, 9, 1], "texture": "#3"},
				"south": {"uv": [12, 4, 13, 5], "texture": "#3"},
				"west": {"uv": [6, 1, 9, 2], "texture": "#3"},
				"up": {"uv": [3, 9, 2, 6], "texture": "#3"},
				"down": {"uv": [4, 6, 3, 9], "texture": "#3"}
			}
		},
		{
			"name": "octagon",
			"from": [7.46373, 2.58039, -16],
			"to": [7.59498, 2.99461, -13.175],
			"rotation": {"angle": 0, "axis": "y", "origin": [7.96373, 2.7875, -13.0875]},
			"faces": {
				"north": {"uv": [5, 12, 6, 13], "texture": "#3"},
				"east": {"uv": [6, 5, 9, 6], "texture": "#3"},
				"south": {"uv": [12, 5, 13, 6], "texture": "#3"},
				"west": {"uv": [6, 6, 9, 7], "texture": "#3"},
				"up": {"uv": [5, 10, 4, 7], "texture": "#3"},
				"down": {"uv": [7, 7, 6, 10], "texture": "#3"}
			}
		},
		{
			"name": "octagon",
			"from": [8.33248, 2.58039, -16],
			"to": [8.46373, 2.99461, -13.175],
			"rotation": {"angle": 45, "axis": "z", "origin": [7.96373, 2.7875, -13.0875]},
			"faces": {
				"north": {"uv": [6, 12, 7, 13], "texture": "#3"},
				"east": {"uv": [7, 3, 10, 4], "texture": "#3"},
				"south": {"uv": [12, 6, 13, 7], "texture": "#3"},
				"west": {"uv": [7, 7, 10, 8], "texture": "#3"},
				"up": {"uv": [1, 11, 0, 8], "texture": "#3"},
				"down": {"uv": [2, 8, 1, 11], "texture": "#3"}
			}
		},
		{
			"name": "octagon",
			"from": [8.33248, 2.58039, -16],
			"to": [8.46373, 2.99461, -13.175],
			"rotation": {"angle": 0, "axis": "y", "origin": [7.96373, 2.7875, -13.0875]},
			"faces": {
				"north": {"uv": [7, 12, 8, 13], "texture": "#3"},
				"east": {"uv": [8, 2, 11, 3], "texture": "#3"},
				"south": {"uv": [12, 7, 13, 8], "texture": "#3"},
				"west": {"uv": [8, 4, 11, 5], "texture": "#3"},
				"up": {"uv": [6, 11, 5, 8], "texture": "#3"},
				"down": {"uv": [8, 8, 7, 11], "texture": "#3"}
			}
		}
	],
	"groups": [
		{
			"name": "octagon",
			"origin": [8, 8, 8],
			"color": 0,
			"nbt": "{}",
			"children": [
				{
					"name": "group",
					"origin": [7.96373, 2.7875, -9.74375],
					"color": 0,
					"nbt": "{}",
					"children": [0, 1, 2, 3, 4, 5, 6, 7, 8, 9, 10, 11, 12, 13, 14, 15]
				}
			]
		}
	]
}